aiophotoprism/__init__.py
aiophotoprism/api.py
aiophotoprism/dictobject.py
aiophotoprism/exceptions.py
aiophotoprism/photoprism.py
aiophotoprism-0.2.0.dist-info/LICENSE
aiophotoprism-0.2.0.dist-info/METADATA
aiophotoprism-0.2.0.dist-info/WHEEL
aiophotoprism-0.2.0.dist-info/top_level.txt
aiophotoprism-0.2.0.dist-info/zip-safe
aiophotoprism-0.2.0.dist-info/RECORD
