Metadata-Version: 2.1
Name: aiophotoprism
Version: 0.2.0
Summary: Asynchronous Python client for the Photoprism REST API
Home-page: https://github.com/zhulik/aiophotoprism
Author: Gleb Sinyavskiy
Author-email: zhulik.gleb@gmail.com
License: The MIT License
Keywords: photoprism,photo,api,aio,async,await
Platform: UNKNOWN
Classifier: Development Status :: 3 - Alpha
Classifier: Intended Audience :: Developers
Classifier: Natural Language :: English
Classifier: License :: OSI Approved :: MIT License
Classifier: Programming Language :: Python :: 3.7
Classifier: Programming Language :: Python :: 3.8
Classifier: Programming Language :: Python :: 3.9
License-File: LICENSE
Requires-Dist: aiohttp (<4.0.0,>=3.7.4)
Requires-Dist: yarl (<2.0.0,>=1.6.3)
